kinto_client/__init__.py
kinto_client/batch.py
kinto_client/cli_utils.py
kinto_client/exceptions.py
kinto_client/replication.py
kinto_client/session.py
kinto_client/utils.py
kinto_client/tests/__init__.py
kinto_client/tests/functional.py
kinto_client/tests/support.py
kinto_client/tests/test_batch.py
kinto_client/tests/test_cli_utils.py
kinto_client/tests/test_client.py
kinto_client/tests/test_endpoints.py
kinto_client/tests/test_replication.py
kinto_client/tests/test_session.py
kinto_client/tests/test_utils.py
kinto_client/tests/config/kinto.ini
kinto_client-5.0.0.dist-info/DESCRIPTION.rst
kinto_client-5.0.0.dist-info/METADATA
kinto_client-5.0.0.dist-info/RECORD
kinto_client-5.0.0.dist-info/WHEEL
kinto_client-5.0.0.dist-info/metadata.json
kinto_client-5.0.0.dist-info/top_level.txt
