Metadata-Version: 2.0
Name: kinto-client
Version: 5.0.0
Summary: Kinto client
Home-page: https://github.com/Kinto/kinto.py/
Author: Mozilla Services
Author-email: storage@mozilla.com
License: Apache License (2.0)
Keywords: web services
Platform: UNKNOWN
Classifier: Programming Language :: Python
Classifier: Programming Language :: Python :: 2
Classifier: Programming Language :: Python :: 2.7
Classifier: Programming Language :: Python :: 3.4
Classifier: Programming Language :: Python :: Implementation :: CPython
Classifier: Topic :: Internet :: WWW/HTTP
Classifier: License :: OSI Approved :: Apache Software License
Requires-Dist: PyOpenSSL
Requires-Dist: ndg-httpsclient
Requires-Dist: pyasn1
Requires-Dist: requests (>=2.8.1)
Requires-Dist: six
Requires-Dist: unidecode
